[
  {
    "name": "icube",
    "rank": 1
  },
  {
    "name": "adrien1018",
    "rank": 2
  },
  {
    "name": "bingxuan9112",
    "rank": 3
  },
  {
    "name": "baluteshih",
    "rank": 4
  },
  {
    "name": "ototot",
    "rank": 5
  },
  {
    "name": "luckyanthonyan",
    "rank": 6
  },
  {
    "name": "fhvirus",
    "rank": 7
  },
  {
    "name": "waynetu",
    "rank": 8
  },
  {
    "name": "valder",
    "rank": 9
  },
  {
    "name": "casperwang",
    "rank": 10
  },
  {
    "name": "edisonhello",
    "rank": 11
  },
  {
    "name": "seanliu",
    "rank": 12
  },
  {
    "name": "justinlai",
    "rank": 13
  },
  {
    "name": "double",
    "rank": 14
  },
  {
    "name": "alan8585",
    "rank": 15
  },
  {
    "name": "rk42745417",
    "rank": 16
  },
  {
    "name": "joe59491",
    "rank": 17
  },
  {
    "name": "nekosyndrome",
    "rank": 18
  },
  {
    "name": "shaman",
    "rank": 19
  },
  {
    "name": "alphabetagama",
    "rank": 20
  },
  {
    "name": "puyuliao",
    "rank": 21
  },
  {
    "name": "harrychang1017",
    "rank": 22
  },
  {
    "name": "tim25871014",
    "rank": 23
  },
  {
    "name": "a00012025",
    "rank": 24
  },
  {
    "name": "anyu",
    "rank": 25
  },
  {
    "name": "warner1129",
    "rank": 26
  },
  {
    "name": "kevin_zhang",
    "rank": 27
  },
  {
    "name": "larrylan",
    "rank": 28
  },
  {
    "name": "polaris",
    "rank": 29
  },
  {
    "name": "visitorikc",
    "rank": 30
  },
  {
    "name": "samsam2310",
    "rank": 31
  },
  {
    "name": "sylveon",
    "rank": 32
  },
  {
    "name": "binsjl",
    "rank": 33
  },
  {
    "name": "tsyr",
    "rank": 34
  },
  {
    "name": "hanayukii",
    "rank": 35
  },
  {
    "name": "harry900831",
    "rank": 36
  },
  {
    "name": "simon3871",
    "rank": 37
  },
  {
    "name": "i_am_noob",
    "rank": 38
  },
  {
    "name": "ltf0501",
    "rank": 39
  },
  {
    "name": "austin990301",
    "rank": 40
  },
  {
    "name": "skylinebaby",
    "rank": 41
  },
  {
    "name": "ck1090915",
    "rank": 42
  },
  {
    "name": "mushroom",
    "rank": 43
  },
  {
    "name": "kerry970176",
    "rank": 44
  },
  {
    "name": "thomasyu",
    "rank": 45
  },
  {
    "name": "peter0303",
    "rank": 46
  },
  {
    "name": "tmwilliamlin168",
    "rank": 47
  },
  {
    "name": "ianwang1204",
    "rank": 48
  },
  {
    "name": "de45amiku",
    "rank": 49
  },
  {
    "name": "momotioj",
    "rank": 50
  },
  {
    "name": "briansu",
    "rank": 51
  },
  {
    "name": "bert30702",
    "rank": 52
  },
  {
    "name": "jerry_chan",
    "rank": 53
  },
  {
    "name": "jim",
    "rank": 54
  },
  {
    "name": "yungyao",
    "rank": 55
  },
  {
    "name": "domen111",
    "rank": 56
  },
  {
    "name": "ashitanokaze",
    "rank": 57
  },
  {
    "name": "ccucumber12",
    "rank": 58
  },
  {
    "name": "chris920318",
    "rank": 59
  },
  {
    "name": "abc864197532",
    "rank": 60
  },
  {
    "name": "lolicon",
    "rank": 61
  },
  {
    "name": "cheissmart",
    "rank": 62
  },
  {
    "name": "sincere",
    "rank": 63
  },
  {
    "name": "bh2142",
    "rank": 64
  },
  {
    "name": "mcyang",
    "rank": 65
  },
  {
    "name": "daniel920712",
    "rank": 66
  },
  {
    "name": "minson123",
    "rank": 67
  },
  {
    "name": "thtsshz",
    "rank": 68
  },
  {
    "name": "tmd910607",
    "rank": 69
  },
  {
    "name": "chyen",
    "rank": 70
  },
  {
    "name": "yjojdkgk5bp",
    "rank": 71
  },
  {
    "name": "eric_xiao",
    "rank": 72
  },
  {
    "name": "ken",
    "rank": 73
  },
  {
    "name": "fsh0524",
    "rank": 74
  },
  {
    "name": "udchen",
    "rank": 75
  },
  {
    "name": "william",
    "rank": 76
  },
  {
    "name": "seal910402",
    "rank": 77
  },
  {
    "name": "wiwiho",
    "rank": 78
  },
  {
    "name": "thanksone",
    "rank": 79
  },
  {
    "name": "tangent",
    "rank": 80
  },
  {
    "name": "lin_shang",
    "rank": 81
  },
  {
    "name": "chenyan",
    "rank": 82
  },
  {
    "name": "tsehsuan1102",
    "rank": 83
  },
  {
    "name": "yp155136",
    "rank": 84
  },
  {
    "name": "kuanyuwei",
    "rank": 85
  },
  {
    "name": "sorahisa",
    "rank": 86
  },
  {
    "name": "hhhhaura",
    "rank": 87
  },
  {
    "name": "emanlaicepsa",
    "rank": 88
  },
  {
    "name": "stcs",
    "rank": 89
  },
  {
    "name": "yesa1791",
    "rank": 90
  },
  {
    "name": "skyfires",
    "rank": 91
  },
  {
    "name": "jeffrey",
    "rank": 92
  },
  {
    "name": "hank0001",
    "rank": 93
  },
  {
    "name": "detaomega",
    "rank": 94
  },
  {
    "name": "achyang",
    "rank": 95
  },
  {
    "name": "marmot0814",
    "rank": 96
  },
  {
    "name": "iris2617",
    "rank": 97
  },
  {
    "name": "iloveimo",
    "rank": 98
  },
  {
    "name": "cmes31419",
    "rank": 99
  },
  {
    "name": "joylintp",
    "rank": 100
  },
  {
    "name": "giver",
    "rank": 101
  },
  {
    "name": "c10555066",
    "rank": 102
  },
  {
    "name": "gary940610",
    "rank": 103
  },
  {
    "name": "w4ynebbcola",
    "rank": 104
  },
  {
    "name": "prprprpony",
    "rank": 105
  },
  {
    "name": "k034006",
    "rank": 106
  },
  {
    "name": "h1de_in_bruh",
    "rank": 107
  },
  {
    "name": "btlllbill",
    "rank": 108
  },
  {
    "name": "lltzpp",
    "rank": 109
  },
  {
    "name": "lin930924",
    "rank": 110
  },
  {
    "name": "ken1277725",
    "rank": 111
  },
  {
    "name": "guagua",
    "rank": 112
  },
  {
    "name": "mudream4869",
    "rank": 113
  },
  {
    "name": "ypl891218",
    "rank": 114
  },
  {
    "name": "boook",
    "rank": 115
  },
  {
    "name": "archerop",
    "rank": 116
  },
  {
    "name": "yazmau999",
    "rank": 117
  },
  {
    "name": "howard0027",
    "rank": 118
  },
  {
    "name": "doaob",
    "rank": 119
  },
  {
    "name": "hansonyu123",
    "rank": 120
  },
  {
    "name": "jizz1999119",
    "rank": 121
  },
  {
    "name": "yojahuang",
    "rank": 122
  },
  {
    "name": "alexwang0423",
    "rank": 123
  },
  {
    "name": "doomhammer",
    "rank": 124
  },
  {
    "name": "evan85910907",
    "rank": 125
  },
  {
    "name": "littlecat",
    "rank": 126
  },
  {
    "name": "tester_101",
    "rank": 127
  },
  {
    "name": "hno2",
    "rank": 128
  },
  {
    "name": "usjl",
    "rank": 129
  },
  {
    "name": "fysty",
    "rank": 130
  },
  {
    "name": "jass921026",
    "rank": 131
  },
  {
    "name": "hfy880916",
    "rank": 132
  },
  {
    "name": "jeremy624",
    "rank": 133
  },
  {
    "name": "sam571128",
    "rank": 134
  },
  {
    "name": "petjelinux",
    "rank": 135
  },
  {
    "name": "yes",
    "rank": 136
  },
  {
    "name": "leo900807",
    "rank": 137
  },
  {
    "name": "albert0liu0",
    "rank": 138
  },
  {
    "name": "yayun146",
    "rank": 139
  },
  {
    "name": "horacelin",
    "rank": 140
  },
  {
    "name": "kyle",
    "rank": 141
  },
  {
    "name": "ivywang123",
    "rank": 142
  },
  {
    "name": "gkevinyen5418",
    "rank": 143
  },
  {
    "name": "eethan1",
    "rank": 144
  },
  {
    "name": "hhhaaahhhaa",
    "rank": 145
  },
  {
    "name": "gilbert12",
    "rank": 146
  },
  {
    "name": "littlecube",
    "rank": 147
  },
  {
    "name": "arutoriawhite",
    "rank": 148
  },
  {
    "name": "ck1080012",
    "rank": 149
  },
  {
    "name": "lonelysam",
    "rank": 150
  },
  {
    "name": "escape",
    "rank": 151
  },
  {
    "name": "dot",
    "rank": 152
  },
  {
    "name": "moulin487",
    "rank": 153
  },
  {
    "name": "arbuz",
    "rank": 154
  },
  {
    "name": "ck1090174",
    "rank": 155
  },
  {
    "name": "vincent10400094",
    "rank": 156
  },
  {
    "name": "paul_liao",
    "rank": 157
  },
  {
    "name": "vincent97198",
    "rank": 158
  },
  {
    "name": "hq8398",
    "rank": 159
  },
  {
    "name": "warrenwang",
    "rank": 160
  },
  {
    "name": "zionhuang",
    "rank": 161
  },
  {
    "name": "royyaha",
    "rank": 162
  },
  {
    "name": "kevin500001",
    "rank": 163
  },
  {
    "name": "gtyuse",
    "rank": 164
  },
  {
    "name": "csjl",
    "rank": 165
  },
  {
    "name": "iceysheep157",
    "rank": 166
  },
  {
    "name": "tocknicsu",
    "rank": 167
  },
  {
    "name": "hide_on_bitch",
    "rank": 168
  },
  {
    "name": "tsguan11",
    "rank": 169
  },
  {
    "name": "pi_tw",
    "rank": 170
  },
  {
    "name": "jill880829",
    "rank": 171
  },
  {
    "name": "nonamefour0210",
    "rank": 172
  },
  {
    "name": "nathanlee726",
    "rank": 173
  },
  {
    "name": "thomaswang",
    "rank": 174
  },
  {
    "name": "unknown",
    "rank": 175
  },
  {
    "name": "elvish",
    "rank": 176
  },
  {
    "name": "ianck",
    "rank": 177
  },
  {
    "name": "leo",
    "rank": 178
  },
  {
    "name": "kennyfs",
    "rank": 179
  },
  {
    "name": "kennywang",
    "rank": 180
  },
  {
    "name": "arctan",
    "rank": 181
  },
  {
    "name": "bc4iaa",
    "rank": 182
  },
  {
    "name": "ccbeginner",
    "rank": 183
  },
  {
    "name": "andy89923",
    "rank": 184
  },
  {
    "name": "pixelcat",
    "rank": 185
  },
  {
    "name": "star_platinum",
    "rank": 186
  },
  {
    "name": "shaymin",
    "rank": 187
  },
  {
    "name": "peienwu",
    "rank": 188
  },
  {
    "name": "devtnuier",
    "rank": 189
  },
  {
    "name": "maple3142",
    "rank": 190
  },
  {
    "name": "show50726",
    "rank": 191
  },
  {
    "name": "astrayt",
    "rank": 192
  },
  {
    "name": "teddy",
    "rank": 193
  },
  {
    "name": "kartta080197",
    "rank": 194
  },
  {
    "name": "hiiragi4000",
    "rank": 195
  },
  {
    "name": "seanhung21",
    "rank": 196
  },
  {
    "name": "timothyyee",
    "rank": 197
  },
  {
    "name": "ej0cl6",
    "rank": 198
  },
  {
    "name": "wilsonlu93",
    "rank": 199
  },
  {
    "name": "hshua",
    "rank": 200
  },
  {
    "name": "solocat",
    "rank": 201
  },
  {
    "name": "andy3466",
    "rank": 202
  },
  {
    "name": "falcon",
    "rank": 203
  },
  {
    "name": "rareone0602",
    "rank": 204
  },
  {
    "name": "derek",
    "rank": 205
  },
  {
    "name": "benson2005",
    "rank": 206
  },
  {
    "name": "tn781927",
    "rank": 207
  },
  {
    "name": "hsnu_153319",
    "rank": 208
  },
  {
    "name": "yuihuang",
    "rank": 209
  },
  {
    "name": "scottchou1018",
    "rank": 210
  },
  {
    "name": "biology22",
    "rank": 211
  },
  {
    "name": "franklee1015",
    "rank": 212
  },
  {
    "name": "yesray0216",
    "rank": 213
  },
  {
    "name": "fireball0424",
    "rank": 214
  },
  {
    "name": "zrn-coding",
    "rank": 215
  },
  {
    "name": "red_rainowo",
    "rank": 216
  },
  {
    "name": "s94vu183",
    "rank": 217
  },
  {
    "name": "becaido",
    "rank": 218
  },
  {
    "name": "vincent550102",
    "rank": 219
  },
  {
    "name": "dragonphoenix",
    "rank": 220
  },
  {
    "name": "hans0342",
    "rank": 221
  },
  {
    "name": "lawrence",
    "rank": 222
  },
  {
    "name": "darry140",
    "rank": 223
  },
  {
    "name": "jeter",
    "rank": 224
  },
  {
    "name": "andybear",
    "rank": 225
  },
  {
    "name": "raylu",
    "rank": 226
  },
  {
    "name": "william40614",
    "rank": 227
  },
  {
    "name": "posen1001024",
    "rank": 228
  },
  {
    "name": "cornelius",
    "rank": 229
  },
  {
    "name": "tico88612",
    "rank": 230
  },
  {
    "name": "william1016",
    "rank": 231
  },
  {
    "name": "cthbst",
    "rank": 232
  },
  {
    "name": "chenxeney",
    "rank": 233
  },
  {
    "name": "bltsandwich",
    "rank": 234
  },
  {
    "name": "yunnn",
    "rank": 235
  },
  {
    "name": "bestlulutw",
    "rank": 236
  },
  {
    "name": "fr1234",
    "rank": 237
  },
  {
    "name": "hubertc1",
    "rank": 238
  },
  {
    "name": "jayinnn",
    "rank": 239
  },
  {
    "name": "willypillow",
    "rank": 240
  },
  {
    "name": "h.c.h.",
    "rank": 241
  },
  {
    "name": "w80707",
    "rank": 242
  },
  {
    "name": "jammychiou1",
    "rank": 243
  },
  {
    "name": "wayne_yan",
    "rank": 244
  },
  {
    "name": "intmain",
    "rank": 245
  },
  {
    "name": "dufu",
    "rank": 246
  },
  {
    "name": "gummybearr",
    "rank": 247
  },
  {
    "name": "normaler",
    "rank": 248
  },
  {
    "name": "crazytim",
    "rank": 249
  },
  {
    "name": "asddzxcc1856",
    "rank": 250
  },
  {
    "name": "gtcoding",
    "rank": 251
  },
  {
    "name": "siangyu",
    "rank": 252
  },
  {
    "name": "allen9667",
    "rank": 253
  },
  {
    "name": "cfikasear",
    "rank": 254
  },
  {
    "name": "tingyu1215",
    "rank": 255
  },
  {
    "name": "cgsh11014",
    "rank": 256
  },
  {
    "name": "mark31408a",
    "rank": 257
  },
  {
    "name": "asd0026568956",
    "rank": 258
  },
  {
    "name": "austin880625",
    "rank": 259
  },
  {
    "name": "kjl",
    "rank": 260
  },
  {
    "name": "osinoyan",
    "rank": 261
  },
  {
    "name": "jackyliuxx",
    "rank": 262
  },
  {
    "name": "jacky860226",
    "rank": 263
  },
  {
    "name": "willy",
    "rank": 264
  },
  {
    "name": "waffle1223112",
    "rank": 265
  },
  {
    "name": "mirror",
    "rank": 266
  },
  {
    "name": "spng",
    "rank": 267
  },
  {
    "name": "a23248630",
    "rank": 268
  },
  {
    "name": "dreamoon",
    "rank": 269
  },
  {
    "name": "kurtis",
    "rank": 270
  },
  {
    "name": "rober",
    "rank": 271
  },
  {
    "name": "cknini",
    "rank": 272
  },
  {
    "name": "isha21700",
    "rank": 273
  },
  {
    "name": "yuhung94",
    "rank": 274
  },
  {
    "name": "akira",
    "rank": 275
  },
  {
    "name": "a127000555",
    "rank": 276
  },
  {
    "name": "moeloli",
    "rank": 277
  },
  {
    "name": "mm357951",
    "rank": 278
  },
  {
    "name": "brucejian",
    "rank": 279
  },
  {
    "name": "le9018468",
    "rank": 280
  },
  {
    "name": "gamegame",
    "rank": 281
  },
  {
    "name": "hank940115",
    "rank": 282
  },
  {
    "name": "ggh93234999",
    "rank": 283
  },
  {
    "name": "redleaf23477",
    "rank": 284
  },
  {
    "name": "fsps60312",
    "rank": 285
  },
  {
    "name": "alpschen",
    "rank": 286
  },
  {
    "name": "felixtuan",
    "rank": 287
  },
  {
    "name": "s094392",
    "rank": 288
  },
  {
    "name": "alechuang98",
    "rank": 289
  },
  {
    "name": "yuxin12345",
    "rank": 290
  },
  {
    "name": "nevikw39",
    "rank": 291
  },
  {
    "name": "eason8190",
    "rank": 292
  },
  {
    "name": "martiancomputer",
    "rank": 293
  },
  {
    "name": "jerometh",
    "rank": 294
  },
  {
    "name": "k1050223",
    "rank": 295
  },
  {
    "name": "nike310155",
    "rank": 296
  },
  {
    "name": "emilia",
    "rank": 297
  },
  {
    "name": "ar-oh",
    "rank": 298
  },
  {
    "name": "rrr",
    "rank": 299
  },
  {
    "name": "cindylinz",
    "rank": 300
  },
  {
    "name": "oao",
    "rank": 301
  },
  {
    "name": "kylelin",
    "rank": 302
  },
  {
    "name": "eopxd",
    "rank": 303
  },
  {
    "name": "ggininder",
    "rank": 304
  },
  {
    "name": "hash",
    "rank": 305
  },
  {
    "name": "asd768999",
    "rank": 306
  },
  {
    "name": "angrybird9415",
    "rank": 307
  },
  {
    "name": "gggiovanni",
    "rank": 308
  },
  {
    "name": "konchin",
    "rank": 309
  },
  {
    "name": "thegloomysky",
    "rank": 310
  },
  {
    "name": "fivefiftyfive",
    "rank": 311
  },
  {
    "name": "xuan",
    "rank": 312
  },
  {
    "name": "a40693651",
    "rank": 313
  },
  {
    "name": "jd3",
    "rank": 314
  },
  {
    "name": "ganonuchiha",
    "rank": 315
  },
  {
    "name": "ststone1687",
    "rank": 316
  },
  {
    "name": "lanyan0202",
    "rank": 317
  },
  {
    "name": "yao99",
    "rank": 318
  },
  {
    "name": "henry",
    "rank": 319
  },
  {
    "name": "kevinorjohn",
    "rank": 320
  },
  {
    "name": "thundercold",
    "rank": 321
  },
  {
    "name": "dapu81000",
    "rank": 322
  },
  {
    "name": "chanhanyi0923",
    "rank": 323
  },
  {
    "name": "kellyfang",
    "rank": 324
  },
  {
    "name": "pixeleston",
    "rank": 325
  },
  {
    "name": "silvernegi",
    "rank": 326
  },
  {
    "name": "weiweibrad",
    "rank": 327
  },
  {
    "name": "sheepranger",
    "rank": 328
  },
  {
    "name": "sean64",
    "rank": 329
  },
  {
    "name": "yicheng484",
    "rank": 330
  },
  {
    "name": "john60513",
    "rank": 331
  },
  {
    "name": "pqc",
    "rank": 332
  },
  {
    "name": "haruto810198",
    "rank": 333
  },
  {
    "name": "flash",
    "rank": 334
  },
  {
    "name": "michaelwan0906",
    "rank": 335
  },
  {
    "name": "billhung56",
    "rank": 336
  },
  {
    "name": "alan",
    "rank": 337
  },
  {
    "name": "rick6tw",
    "rank": 338
  },
  {
    "name": "hawaii",
    "rank": 339
  },
  {
    "name": "ianlo0511",
    "rank": 340
  },
  {
    "name": "harrykuo1",
    "rank": 341
  },
  {
    "name": "eheu",
    "rank": 342
  },
  {
    "name": "t1016d",
    "rank": 343
  },
  {
    "name": "hsnu510148",
    "rank": 344
  },
  {
    "name": "justforfun",
    "rank": 345
  },
  {
    "name": "eayaps1788",
    "rank": 346
  },
  {
    "name": "f1f21313",
    "rank": 347
  },
  {
    "name": "mtmatt",
    "rank": 348
  },
  {
    "name": "ashleyyen",
    "rank": 349
  },
  {
    "name": "huang_bo_bing",
    "rank": 350
  },
  {
    "name": "skttty",
    "rank": 351
  },
  {
    "name": "terry25031069",
    "rank": 352
  },
  {
    "name": "wcwu",
    "rank": 353
  },
  {
    "name": "csy",
    "rank": 354
  },
  {
    "name": "leofu",
    "rank": 355
  },
  {
    "name": "ann",
    "rank": 356
  },
  {
    "name": "user-howard",
    "rank": 357
  },
  {
    "name": "hfchou",
    "rank": 358
  },
  {
    "name": "aaa1234",
    "rank": 359
  },
  {
    "name": "deron",
    "rank": 360
  },
  {
    "name": "snowman",
    "rank": 361
  },
  {
    "name": "autofindingbot",
    "rank": 362
  },
  {
    "name": "j25300453",
    "rank": 363
  },
  {
    "name": "nctufox",
    "rank": 364
  },
  {
    "name": "kevin4314",
    "rank": 365
  },
  {
    "name": "syl123456",
    "rank": 366
  },
  {
    "name": "kelly",
    "rank": 367
  },
  {
    "name": "wanling1212",
    "rank": 368
  },
  {
    "name": "printhelloworld",
    "rank": 369
  },
  {
    "name": "richardliang19",
    "rank": 370
  },
  {
    "name": "qwe854896",
    "rank": 371
  },
  {
    "name": "robert1003",
    "rank": 372
  },
  {
    "name": "arzer",
    "rank": 373
  },
  {
    "name": "marslai24",
    "rank": 374
  },
  {
    "name": "aliphlya",
    "rank": 375
  },
  {
    "name": "acchou",
    "rank": 376
  },
  {
    "name": "fcrh",
    "rank": 377
  },
  {
    "name": "anlialtting",
    "rank": 378
  },
  {
    "name": "maxwill",
    "rank": 379
  },
  {
    "name": "a20000917",
    "rank": 380
  },
  {
    "name": "w86763777",
    "rank": 381
  },
  {
    "name": "arod571431",
    "rank": 382
  },
  {
    "name": "dienruei123",
    "rank": 383
  },
  {
    "name": "n14a7",
    "rank": 384
  },
  {
    "name": "caroline",
    "rank": 385
  },
  {
    "name": "calvin9403",
    "rank": 386
  },
  {
    "name": "goro",
    "rank": 387
  },
  {
    "name": "ricky9667",
    "rank": 388
  },
  {
    "name": "chenrui",
    "rank": 389
  },
  {
    "name": "jasper0314",
    "rank": 390
  },
  {
    "name": "mno2",
    "rank": 391
  },
  {
    "name": "tnt870087",
    "rank": 392
  },
  {
    "name": "mouyilai",
    "rank": 393
  },
  {
    "name": "dandan",
    "rank": 394
  },
  {
    "name": "huaishing",
    "rank": 395
  },
  {
    "name": "ck1060320",
    "rank": 396
  },
  {
    "name": "meerkat",
    "rank": 397
  },
  {
    "name": "pamela",
    "rank": 398
  },
  {
    "name": "joey",
    "rank": 399
  },
  {
    "name": "vincent40416",
    "rank": 400
  },
  {
    "name": "davidkuo3",
    "rank": 401
  },
  {
    "name": "stickman0131",
    "rank": 402
  },
  {
    "name": "peterxcli",
    "rank": 403
  },
  {
    "name": "fishball",
    "rank": 404
  },
  {
    "name": "belong",
    "rank": 405
  },
  {
    "name": "freshman0213",
    "rank": 406
  },
  {
    "name": "pandix",
    "rank": 407
  },
  {
    "name": "onehundredping",
    "rank": 408
  },
  {
    "name": "jellyfish",
    "rank": 409
  },
  {
    "name": "pilgrimallen",
    "rank": 410
  },
  {
    "name": "qwq",
    "rank": 411
  },
  {
    "name": "bentley0928",
    "rank": 412
  },
  {
    "name": "m24639297",
    "rank": 413
  },
  {
    "name": "niko",
    "rank": 414
  },
  {
    "name": "swear",
    "rank": 415
  },
  {
    "name": "yucsh",
    "rank": 416
  },
  {
    "name": "easonsfriend",
    "rank": 417
  },
  {
    "name": "rice9547",
    "rank": 418
  },
  {
    "name": "wangsmallsmooth",
    "rank": 419
  },
  {
    "name": "bmk2451",
    "rank": 420
  },
  {
    "name": "ppetter1025",
    "rank": 421
  },
  {
    "name": "asfhiol",
    "rank": 422
  },
  {
    "name": "cpcap",
    "rank": 423
  },
  {
    "name": "peikaiyeh",
    "rank": 424
  },
  {
    "name": "anthonylee",
    "rank": 425
  },
  {
    "name": "zaneyu",
    "rank": 426
  },
  {
    "name": "tmpss96373",
    "rank": 427
  },
  {
    "name": "hsiaoe",
    "rank": 428
  },
  {
    "name": "simonsici",
    "rank": 429
  },
  {
    "name": "kasermin",
    "rank": 430
  },
  {
    "name": "yeedrag",
    "rank": 431
  },
  {
    "name": "davidliu",
    "rank": 432
  },
  {
    "name": "erichung",
    "rank": 433
  },
  {
    "name": "hsieyitai",
    "rank": 434
  },
  {
    "name": "soytw",
    "rank": 435
  },
  {
    "name": "johnson30708",
    "rank": 436
  },
  {
    "name": "rwqlisa",
    "rank": 437
  },
  {
    "name": "tonywei",
    "rank": 438
  },
  {
    "name": "johnny87087",
    "rank": 439
  },
  {
    "name": "dube116",
    "rank": 440
  },
  {
    "name": "morganlee",
    "rank": 441
  },
  {
    "name": "c2251393",
    "rank": 442
  },
  {
    "name": "ck10700972",
    "rank": 443
  },
  {
    "name": "bear890707",
    "rank": 444
  },
  {
    "name": "aalexx_s",
    "rank": 445
  },
  {
    "name": "w181496",
    "rank": 446
  },
  {
    "name": "kevin47",
    "rank": 447
  },
  {
    "name": "vs_noob",
    "rank": 448
  },
  {
    "name": "andy920262",
    "rank": 449
  },
  {
    "name": "kobe121212",
    "rank": 450
  },
  {
    "name": "thetom0514",
    "rank": 451
  },
  {
    "name": "sandwich",
    "rank": 452
  },
  {
    "name": "alicetingchen",
    "rank": 453
  },
  {
    "name": "howard41436",
    "rank": 454
  },
  {
    "name": "alex022820",
    "rank": 455
  },
  {
    "name": "firstonfur",
    "rank": 456
  },
  {
    "name": "jw910731",
    "rank": 457
  },
  {
    "name": "dannyboy20031204",
    "rank": 458
  },
  {
    "name": "tiffany0108",
    "rank": 459
  },
  {
    "name": "felicityliu",
    "rank": 460
  },
  {
    "name": "nicky",
    "rank": 461
  },
  {
    "name": "wjeng",
    "rank": 462
  },
  {
    "name": "yu2001",
    "rank": 463
  },
  {
    "name": "fg10631325",
    "rank": 464
  },
  {
    "name": "yennnn",
    "rank": 465
  },
  {
    "name": "dapplingdot721",
    "rank": 466
  },
  {
    "name": "michael0432",
    "rank": 467
  },
  {
    "name": "creeperwsz",
    "rank": 468
  },
  {
    "name": "cc910905",
    "rank": 469
  },
  {
    "name": "jason7777",
    "rank": 470
  },
  {
    "name": "murphylawvictim",
    "rank": 471
  },
  {
    "name": "ghost",
    "rank": 472
  },
  {
    "name": "music960633",
    "rank": 473
  },
  {
    "name": "houzhibin",
    "rank": 474
  },
  {
    "name": "jiahonglin",
    "rank": 475
  },
  {
    "name": "felicity",
    "rank": 476
  },
  {
    "name": "wearelp",
    "rank": 477
  },
  {
    "name": "hsu7021",
    "rank": 478
  },
  {
    "name": "tcc",
    "rank": 479
  },
  {
    "name": "kyoya3510",
    "rank": 480
  },
  {
    "name": "grorge",
    "rank": 481
  },
  {
    "name": "sc211",
    "rank": 482
  },
  {
    "name": "iplocker",
    "rank": 483
  },
  {
    "name": "bryan22244",
    "rank": 484
  },
  {
    "name": "arthur",
    "rank": 485
  },
  {
    "name": "tomatoba",
    "rank": 486
  },
  {
    "name": "louiss72",
    "rank": 487
  },
  {
    "name": "s106062228",
    "rank": 488
  },
  {
    "name": "choder",
    "rank": 489
  },
  {
    "name": "kakalan123",
    "rank": 490
  },
  {
    "name": "eggman",
    "rank": 491
  },
  {
    "name": "chhu0830",
    "rank": 492
  },
  {
    "name": "ygi0427",
    "rank": 493
  },
  {
    "name": "huz0752",
    "rank": 494
  },
  {
    "name": "pink_banana",
    "rank": 495
  },
  {
    "name": "olddog",
    "rank": 496
  },
  {
    "name": "howell",
    "rank": 497
  },
  {
    "name": "zireael",
    "rank": 498
  },
  {
    "name": "asdf79852",
    "rank": 499
  },
  {
    "name": "blueleaf",
    "rank": 500
  },
  {
    "name": "yiec2538",
    "rank": 501
  },
  {
    "name": "jwang0306",
    "rank": 502
  },
  {
    "name": "johnchen902",
    "rank": 503
  },
  {
    "name": "chichitw",
    "rank": 504
  },
  {
    "name": "googleak28282",
    "rank": 505
  },
  {
    "name": "j3soon",
    "rank": 506
  },
  {
    "name": "stranger_0229",
    "rank": 507
  },
  {
    "name": "kevin3923",
    "rank": 508
  },
  {
    "name": "jamespeng",
    "rank": 509
  },
  {
    "name": "whyuwhyu",
    "rank": 510
  },
  {
    "name": "hiwang123",
    "rank": 511
  },
  {
    "name": "ginothedog01",
    "rank": 512
  },
  {
    "name": "user1519",
    "rank": 513
  },
  {
    "name": "charlie890414",
    "rank": 514
  },
  {
    "name": "yuusha",
    "rank": 515
  },
  {
    "name": "max990",
    "rank": 516
  },
  {
    "name": "waynesu",
    "rank": 517
  },
  {
    "name": "ss8651twtw",
    "rank": 518
  },
  {
    "name": "aoi",
    "rank": 519
  },
  {
    "name": "lemonlemon1001",
    "rank": 520
  },
  {
    "name": "samzhang",
    "rank": 521
  },
  {
    "name": "fleroviumfl",
    "rank": 522
  },
  {
    "name": "tuttut",
    "rank": 523
  },
  {
    "name": "ck10301050",
    "rank": 524
  },
  {
    "name": "wuming",
    "rank": 525
  },
  {
    "name": "hsu",
    "rank": 526
  },
  {
    "name": "subarya",
    "rank": 527
  },
  {
    "name": "gtr0107",
    "rank": 528
  },
  {
    "name": "onekind",
    "rank": 529
  },
  {
    "name": "asme0405",
    "rank": 530
  },
  {
    "name": "aaafff222",
    "rank": 531
  },
  {
    "name": "b070206",
    "rank": 532
  },
  {
    "name": "tom2003611",
    "rank": 533
  },
  {
    "name": "hoou8547",
    "rank": 534
  },
  {
    "name": "chenkb",
    "rank": 535
  },
  {
    "name": "bensonqb",
    "rank": 536
  },
  {
    "name": "yoisaaceee",
    "rank": 537
  },
  {
    "name": "tearing0624",
    "rank": 538
  },
  {
    "name": "cocaine1234",
    "rank": 539
  },
  {
    "name": "danielwu",
    "rank": 540
  },
  {
    "name": "vagrantlike",
    "rank": 541
  },
  {
    "name": "leelin2602",
    "rank": 542
  },
  {
    "name": "ching",
    "rank": 543
  },
  {
    "name": "greenteab",
    "rank": 544
  },
  {
    "name": "s5590220001",
    "rank": 545
  },
  {
    "name": "brianlee",
    "rank": 546
  },
  {
    "name": "alexstrasza",
    "rank": 547
  },
  {
    "name": "ipj",
    "rank": 548
  },
  {
    "name": "tzuchunchen",
    "rank": 549
  },
  {
    "name": "zen",
    "rank": 550
  },
  {
    "name": "niorehkids",
    "rank": 551
  },
  {
    "name": "ivanlin",
    "rank": 552
  },
  {
    "name": "ryan40426",
    "rank": 553
  },
  {
    "name": "anonymous",
    "rank": 554
  },
  {
    "name": "brotherhong",
    "rank": 555
  },
  {
    "name": "sheepman",
    "rank": 556
  },
  {
    "name": "twinklestar03",
    "rank": 557
  },
  {
    "name": "asd",
    "rank": 558
  },
  {
    "name": "brianhsu7476",
    "rank": 559
  },
  {
    "name": "dadalakun25",
    "rank": 560
  },
  {
    "name": "yth",
    "rank": 561
  },
  {
    "name": "es811066",
    "rank": 562
  },
  {
    "name": "fongshou93220",
    "rank": 563
  },
  {
    "name": "excfergodst",
    "rank": 564
  },
  {
    "name": "chi_yei",
    "rank": 565
  },
  {
    "name": "qoodboop",
    "rank": 566
  },
  {
    "name": "exble",
    "rank": 567
  },
  {
    "name": "penguin71630",
    "rank": 568
  },
  {
    "name": "erica1327",
    "rank": 569
  },
  {
    "name": "swagger0413",
    "rank": 570
  },
  {
    "name": "fenzhang",
    "rank": 571
  },
  {
    "name": "erictsengty",
    "rank": 572
  },
  {
    "name": "franklee123456",
    "rank": 573
  },
  {
    "name": "allem40306",
    "rank": 574
  },
  {
    "name": "esrever",
    "rank": 575
  },
  {
    "name": "brianh",
    "rank": 576
  },
  {
    "name": "howiechen",
    "rank": 577
  },
  {
    "name": "brant",
    "rank": 578
  },
  {
    "name": "waynekaowyk",
    "rank": 579
  },
  {
    "name": "tim360724",
    "rank": 580
  },
  {
    "name": "toad",
    "rank": 581
  },
  {
    "name": "asdfg",
    "rank": 582
  },
  {
    "name": "cchao",
    "rank": 583
  },
  {
    "name": "fdhsrex",
    "rank": 584
  },
  {
    "name": "eric2969",
    "rank": 585
  },
  {
    "name": "poao899",
    "rank": 586
  },
  {
    "name": "danieltzeng",
    "rank": 587
  },
  {
    "name": "yikuo",
    "rank": 588
  },
  {
    "name": "mixar",
    "rank": 589
  },
  {
    "name": "yyspencer",
    "rank": 590
  },
  {
    "name": "asdaxmold",
    "rank": 591
  },
  {
    "name": "popcorn",
    "rank": 592
  },
  {
    "name": "tioj56565656",
    "rank": 593
  },
  {
    "name": "hzlin",
    "rank": 594
  },
  {
    "name": "cutierabbit",
    "rank": 595
  },
  {
    "name": "horikita",
    "rank": 596
  },
  {
    "name": "jimmy",
    "rank": 597
  },
  {
    "name": "tsukiyoru0820",
    "rank": 598
  },
  {
    "name": "cookie197",
    "rank": 599
  },
  {
    "name": "milkbottle",
    "rank": 600
  },
  {
    "name": "oalieno",
    "rank": 601
  },
  {
    "name": "potassium",
    "rank": 602
  },
  {
    "name": "eclipse",
    "rank": 603
  },
  {
    "name": "dof",
    "rank": 604
  },
  {
    "name": "grason",
    "rank": 605
  },
  {
    "name": "samuel21119",
    "rank": 606
  },
  {
    "name": "eheart",
    "rank": 607
  },
  {
    "name": "ioumu6",
    "rank": 608
  },
  {
    "name": "squaremelon",
    "rank": 609
  },
  {
    "name": "pingchungchang",
    "rank": 610
  },
  {
    "name": "janet_hsieh",
    "rank": 611
  },
  {
    "name": "lightbulb12294",
    "rank": 612
  },
  {
    "name": "ryan",
    "rank": 613
  },
  {
    "name": "waynn",
    "rank": 614
  },
  {
    "name": "nnaracy",
    "rank": 615
  },
  {
    "name": "brian93",
    "rank": 616
  },
  {
    "name": "eggtang92",
    "rank": 617
  },
  {
    "name": "jackyname1",
    "rank": 618
  },
  {
    "name": "adson",
    "rank": 619
  },
  {
    "name": "pqbd",
    "rank": 620
  },
  {
    "name": "qwe1688541",
    "rank": 621
  },
  {
    "name": "lnishan",
    "rank": 622
  },
  {
    "name": "antoniohou",
    "rank": 623
  },
  {
    "name": "beanels01",
    "rank": 624
  },
  {
    "name": "k014689",
    "rank": 625
  },
  {
    "name": "cwhuang1937",
    "rank": 626
  },
  {
    "name": "ken890126",
    "rank": 627
  },
  {
    "name": "albertchang",
    "rank": 628
  },
  {
    "name": "cwl",
    "rank": 629
  },
  {
    "name": "bear1222",
    "rank": 630
  },
  {
    "name": "sam_hao",
    "rank": 631
  },
  {
    "name": "fshuen",
    "rank": 632
  },
  {
    "name": "kent1446",
    "rank": 633
  },
  {
    "name": "zsgtest",
    "rank": 634
  },
  {
    "name": "tewei",
    "rank": 635
  },
  {
    "name": "duckingod",
    "rank": 636
  },
  {
    "name": "qwasezrdx",
    "rank": 637
  },
  {
    "name": "illilli",
    "rank": 638
  },
  {
    "name": "testingj",
    "rank": 639
  },
  {
    "name": "emiliafirst",
    "rank": 640
  },
  {
    "name": "alice20070409",
    "rank": 641
  },
  {
    "name": "ck1070979",
    "rank": 642
  },
  {
    "name": "arthurtsai",
    "rank": 643
  },
  {
    "name": "light655",
    "rank": 644
  },
  {
    "name": "agritite",
    "rank": 645
  },
  {
    "name": "secret937183",
    "rank": 646
  },
  {
    "name": "excellent",
    "rank": 647
  },
  {
    "name": "pojay11523",
    "rank": 648
  },
  {
    "name": "skywalker",
    "rank": 649
  },
  {
    "name": "ethanl0518",
    "rank": 650
  },
  {
    "name": "howardkno3",
    "rank": 651
  },
  {
    "name": "henrytsui",
    "rank": 652
  },
  {
    "name": "chsh710754",
    "rank": 653
  },
  {
    "name": "oscar10261",
    "rank": 654
  },
  {
    "name": "lovelypasta",
    "rank": 655
  },
  {
    "name": "annshinewu",
    "rank": 656
  },
  {
    "name": "cycatz",
    "rank": 657
  },
  {
    "name": "snoopy1999",
    "rank": 658
  },
  {
    "name": "dawae",
    "rank": 659
  },
  {
    "name": "bang",
    "rank": 660
  },
  {
    "name": "colten",
    "rank": 661
  },
  {
    "name": "b07902111",
    "rank": 662
  },
  {
    "name": "oliverhua",
    "rank": 663
  },
  {
    "name": "conan1412",
    "rank": 664
  },
  {
    "name": "jackie22chen",
    "rank": 665
  },
  {
    "name": "dc1020090",
    "rank": 666
  },
  {
    "name": "lw310659",
    "rank": 667
  },
  {
    "name": "axs",
    "rank": 668
  },
  {
    "name": "baloneymath",
    "rank": 669
  },
  {
    "name": "marknsc0501",
    "rank": 670
  },
  {
    "name": "yhchen0906",
    "rank": 671
  },
  {
    "name": "happylittle7",
    "rank": 672
  },
  {
    "name": "ternence130",
    "rank": 673
  },
  {
    "name": "shik",
    "rank": 674
  },
  {
    "name": "ken1882",
    "rank": 675
  },
  {
    "name": "wesleychen",
    "rank": 676
  },
  {
    "name": "media1129",
    "rank": 677
  },
  {
    "name": "pclightyear",
    "rank": 678
  },
  {
    "name": "hmtd_taiwan",
    "rank": 679
  },
  {
    "name": "ponywang",
    "rank": 680
  },
  {
    "name": "shioko",
    "rank": 681
  },
  {
    "name": "yekwol",
    "rank": 682
  },
  {
    "name": "creepy_crap",
    "rank": 683
  },
  {
    "name": "knia",
    "rank": 684
  },
  {
    "name": "darrenkung",
    "rank": 685
  },
  {
    "name": "chris",
    "rank": 686
  },
  {
    "name": "tom90tw",
    "rank": 687
  },
  {
    "name": "timmy960072",
    "rank": 688
  },
  {
    "name": "ernestii26",
    "rank": 689
  },
  {
    "name": "sheng120777",
    "rank": 690
  },
  {
    "name": "oliverliu",
    "rank": 691
  },
  {
    "name": "kuo2020",
    "rank": 692
  },
  {
    "name": "cdes58042169",
    "rank": 693
  },
  {
    "name": "st741963456",
    "rank": 694
  },
  {
    "name": "leolee",
    "rank": 695
  },
  {
    "name": "k24680",
    "rank": 696
  },
  {
    "name": "kyhsuan",
    "rank": 697
  },
  {
    "name": "tioj",
    "rank": 698
  },
  {
    "name": "hanklin",
    "rank": 699
  },
  {
    "name": "seanchou",
    "rank": 700
  },
  {
    "name": "b07901034",
    "rank": 701
  },
  {
    "name": "kao",
    "rank": 702
  },
  {
    "name": "tina1998612",
    "rank": 703
  },
  {
    "name": "skylee",
    "rank": 704
  },
  {
    "name": "ejirk321123",
    "rank": 705
  },
  {
    "name": "s3131212",
    "rank": 706
  },
  {
    "name": "jjwu",
    "rank": 707
  },
  {
    "name": "weilam06",
    "rank": 708
  },
  {
    "name": "marco200008",
    "rank": 709
  },
  {
    "name": "minghsu0107",
    "rank": 710
  },
  {
    "name": "derektu123",
    "rank": 711
  },
  {
    "name": "freddy",
    "rank": 712
  },
  {
    "name": "gamerslouis",
    "rank": 713
  },
  {
    "name": "darrell",
    "rank": 714
  },
  {
    "name": "a136489",
    "rank": 715
  },
  {
    "name": "dannyshicar",
    "rank": 716
  },
  {
    "name": "eddy0129",
    "rank": 717
  },
  {
    "name": "jiafong",
    "rank": 718
  },
  {
    "name": "amano_hina",
    "rank": 719
  },
  {
    "name": "doem",
    "rank": 720
  },
  {
    "name": "gunjyo",
    "rank": 721
  },
  {
    "name": "whets",
    "rank": 722
  },
  {
    "name": "shangjung",
    "rank": 723
  },
  {
    "name": "joshua5201",
    "rank": 724
  },
  {
    "name": "crbubble",
    "rank": 725
  },
  {
    "name": "ymliang",
    "rank": 726
  },
  {
    "name": "jonathanhsu",
    "rank": 727
  },
  {
    "name": "hallo1144",
    "rank": 728
  },
  {
    "name": "luyanaa",
    "rank": 729
  },
  {
    "name": "sean123xyz",
    "rank": 730
  },
  {
    "name": "somebody",
    "rank": 731
  },
  {
    "name": "at881005",
    "rank": 732
  },
  {
    "name": "ub33",
    "rank": 733
  },
  {
    "name": "linnil1",
    "rank": 734
  },
  {
    "name": "mdragon",
    "rank": 735
  },
  {
    "name": "pcchou",
    "rank": 736
  },
  {
    "name": "joannachang",
    "rank": 737
  },
  {
    "name": "bunbun22",
    "rank": 738
  },
  {
    "name": "vovo5558",
    "rank": 739
  },
  {
    "name": "nomcc",
    "rank": 740
  },
  {
    "name": "aoeuaoeu",
    "rank": 741
  },
  {
    "name": "bibibi",
    "rank": 742
  },
  {
    "name": "calmtea",
    "rank": 743
  },
  {
    "name": "peterwang",
    "rank": 744
  },
  {
    "name": "loki77",
    "rank": 745
  },
  {
    "name": "tmt514",
    "rank": 746
  },
  {
    "name": "yfshyu168",
    "rank": 747
  },
  {
    "name": "a1301145",
    "rank": 748
  },
  {
    "name": "as535364",
    "rank": 749
  },
  {
    "name": "kbs1127",
    "rank": 750
  },
  {
    "name": "loyi",
    "rank": 751
  },
  {
    "name": "rrrrrrrr",
    "rank": 752
  },
  {
    "name": "jimmychiu",
    "rank": 753
  },
  {
    "name": "shaneliu",
    "rank": 754
  },
  {
    "name": "b88000005",
    "rank": 755
  },
  {
    "name": "s910702s910702",
    "rank": 756
  },
  {
    "name": "a20034294",
    "rank": 757
  },
  {
    "name": "laofu",
    "rank": 758
  },
  {
    "name": "ericlleric",
    "rank": 759
  },
  {
    "name": "ben1102",
    "rank": 760
  },
  {
    "name": "leichonkit",
    "rank": 761
  },
  {
    "name": "slamur",
    "rank": 762
  },
  {
    "name": "jchen8tw",
    "rank": 763
  },
  {
    "name": "b06705003",
    "rank": 764
  },
  {
    "name": "jaychou0129",
    "rank": 765
  },
  {
    "name": "explorer",
    "rank": 766
  },
  {
    "name": "b06902",
    "rank": 767
  },
  {
    "name": "a24203740",
    "rank": 768
  },
  {
    "name": "yilunlin",
    "rank": 769
  },
  {
    "name": "jjjjj19980806",
    "rank": 770
  },
  {
    "name": "r810729",
    "rank": 771
  },
  {
    "name": "e09590959",
    "rank": 772
  },
  {
    "name": "lary",
    "rank": 773
  },
  {
    "name": "winter",
    "rank": 774
  },
  {
    "name": "leelin",
    "rank": 775
  },
  {
    "name": "noob5432",
    "rank": 776
  },
  {
    "name": "ray",
    "rank": 777
  },
  {
    "name": "foreverga",
    "rank": 778
  },
  {
    "name": "soysauce",
    "rank": 779
  },
  {
    "name": "b06406049",
    "rank": 780
  },
  {
    "name": "a120052",
    "rank": 781
  },
  {
    "name": "will",
    "rank": 782
  },
  {
    "name": "lonelygb756",
    "rank": 783
  },
  {
    "name": "dtfcyhd80",
    "rank": 784
  },
  {
    "name": "tangerine001",
    "rank": 785
  },
  {
    "name": "alender777",
    "rank": 786
  },
  {
    "name": "brownbear",
    "rank": 787
  },
  {
    "name": "gophy",
    "rank": 788
  },
  {
    "name": "stanleyotz",
    "rank": 789
  },
  {
    "name": "s1060126",
    "rank": 790
  },
  {
    "name": "kenisgenius",
    "rank": 791
  },
  {
    "name": "hsueh",
    "rank": 792
  },
  {
    "name": "henryranger",
    "rank": 793
  },
  {
    "name": "aszxcv1231",
    "rank": 794
  },
  {
    "name": "cuser1",
    "rank": 795
  },
  {
    "name": "mj0920130972",
    "rank": 796
  },
  {
    "name": "skh",
    "rank": 797
  },
  {
    "name": "yoyo",
    "rank": 798
  },
  {
    "name": "atsushikao",
    "rank": 799
  },
  {
    "name": "jiarong",
    "rank": 800
  },
  {
    "name": "wasterabbit",
    "rank": 801
  },
  {
    "name": "r07722031",
    "rank": 802
  },
  {
    "name": "hcwxd",
    "rank": 803
  },
  {
    "name": "chengbilly",
    "rank": 804
  },
  {
    "name": "a12345678",
    "rank": 805
  },
  {
    "name": "p76081514",
    "rank": 806
  },
  {
    "name": "roger0999",
    "rank": 807
  },
  {
    "name": "jf099005",
    "rank": 808
  },
  {
    "name": "daiyouko",
    "rank": 809
  },
  {
    "name": "cliff",
    "rank": 810
  },
  {
    "name": "estarriol",
    "rank": 811
  },
  {
    "name": "carlos",
    "rank": 812
  },
  {
    "name": "s96103",
    "rank": 813
  },
  {
    "name": "lllllaura",
    "rank": 814
  },
  {
    "name": "yang",
    "rank": 815
  },
  {
    "name": "b04504015",
    "rank": 816
  },
  {
    "name": "benbebobo149",
    "rank": 817
  },
  {
    "name": "davidlee0314",
    "rank": 818
  },
  {
    "name": "u10831016",
    "rank": 819
  },
  {
    "name": "shinkansen942",
    "rank": 820
  },
  {
    "name": "xiurui",
    "rank": 821
  },
  {
    "name": "hsu06010429",
    "rank": 822
  },
  {
    "name": "koe",
    "rank": 823
  },
  {
    "name": "hero1364",
    "rank": 824
  },
  {
    "name": "cleanblue",
    "rank": 825
  },
  {
    "name": "ron19971997",
    "rank": 826
  },
  {
    "name": "james1997102",
    "rank": 827
  },
  {
    "name": "firealone147",
    "rank": 828
  },
  {
    "name": "fatcat",
    "rank": 829
  },
  {
    "name": "oberon",
    "rank": 830
  },
  {
    "name": "wayne86122",
    "rank": 831
  },
  {
    "name": "benson",
    "rank": 832
  },
  {
    "name": "tony",
    "rank": 833
  },
  {
    "name": "leeyc",
    "rank": 834
  },
  {
    "name": "tommy70758465",
    "rank": 835
  },
  {
    "name": "joan040802",
    "rank": 836
  },
  {
    "name": "eroiko",
    "rank": 837
  },
  {
    "name": "zihan",
    "rank": 838
  },
  {
    "name": "inori_code",
    "rank": 839
  },
  {
    "name": "yellowriver",
    "rank": 840
  },
  {
    "name": "william210105",
    "rank": 841
  },
  {
    "name": "ccsccsccs",
    "rank": 842
  },
  {
    "name": "otiyup",
    "rank": 843
  },
  {
    "name": "haha874",
    "rank": 844
  },
  {
    "name": "qwertyuiop0730",
    "rank": 845
  },
  {
    "name": "bigelephant29",
    "rank": 846
  },
  {
    "name": "alex666",
    "rank": 847
  },
  {
    "name": "g5zn98",
    "rank": 848
  },
  {
    "name": "jiulin107141137",
    "rank": 849
  },
  {
    "name": "uwer851",
    "rank": 850
  },
  {
    "name": "chuanmaotou",
    "rank": 851
  },
  {
    "name": "jiewen",
    "rank": 852
  },
  {
    "name": "elm855220",
    "rank": 853
  },
  {
    "name": "excalibur",
    "rank": 854
  },
  {
    "name": "joeyten2000",
    "rank": 855
  },
  {
    "name": "daedluz",
    "rank": 856
  },
  {
    "name": "gods",
    "rank": 857
  },
  {
    "name": "peggy",
    "rank": 858
  },
  {
    "name": "vflc",
    "rank": 859
  },
  {
    "name": "cyderekyeh",
    "rank": 860
  },
  {
    "name": "titusjgrs",
    "rank": 861
  },
  {
    "name": "anthoni",
    "rank": 862
  },
  {
    "name": "williamsw",
    "rank": 863
  },
  {
    "name": "eric7654321",
    "rank": 864
  },
  {
    "name": "roymustang",
    "rank": 865
  },
  {
    "name": "jim841019g",
    "rank": 866
  },
  {
    "name": "jasonqoo543",
    "rank": 867
  },
  {
    "name": "simon5955687",
    "rank": 868
  },
  {
    "name": "l236236f",
    "rank": 869
  },
  {
    "name": "joachim0630",
    "rank": 870
  },
  {
    "name": "st2007320",
    "rank": 871
  },
  {
    "name": "chipcheng",
    "rank": 872
  },
  {
    "name": "joeization",
    "rank": 873
  },
  {
    "name": "zittty",
    "rank": 874
  },
  {
    "name": "ryona",
    "rank": 875
  },
  {
    "name": "chenterry68",
    "rank": 876
  },
  {
    "name": "mauoreo",
    "rank": 877
  },
  {
    "name": "a89997899",
    "rank": 878
  },
  {
    "name": "rfvedc",
    "rank": 879
  },
  {
    "name": "sharntseng",
    "rank": 880
  },
  {
    "name": "zheyu",
    "rank": 881
  },
  {
    "name": "rurengo",
    "rank": 882
  },
  {
    "name": "cwdolphin",
    "rank": 883
  },
  {
    "name": "nonoivan",
    "rank": 884
  },
  {
    "name": "aaronleetw",
    "rank": 885
  },
  {
    "name": "alex",
    "rank": 886
  },
  {
    "name": "rockpelt",
    "rank": 887
  },
  {
    "name": "vincent",
    "rank": 888
  },
  {
    "name": "heeyeo",
    "rank": 889
  },
  {
    "name": "blaketow368",
    "rank": 890
  },
  {
    "name": "zll",
    "rank": 891
  },
  {
    "name": "yhuangcb",
    "rank": 892
  },
  {
    "name": "cheese",
    "rank": 893
  },
  {
    "name": "quan0715",
    "rank": 894
  },
  {
    "name": "yjack",
    "rank": 895
  },
  {
    "name": "oscar_hsu",
    "rank": 896
  },
  {
    "name": "johnny66634345",
    "rank": 897
  },
  {
    "name": "samyang",
    "rank": 898
  },
  {
    "name": "jason_huang",
    "rank": 899
  },
  {
    "name": "bobobo",
    "rank": 900
  },
  {
    "name": "jasonlin1222",
    "rank": 901
  },
  {
    "name": "ououou",
    "rank": 902
  },
  {
    "name": "snow_willow",
    "rank": 903
  },
  {
    "name": "x1001000",
    "rank": 904
  },
  {
    "name": "dannyshi",
    "rank": 905
  },
  {
    "name": "dianyo",
    "rank": 906
  },
  {
    "name": "cywhitebear",
    "rank": 907
  },
  {
    "name": "anthonyliao",
    "rank": 908
  },
  {
    "name": "huangggan",
    "rank": 909
  },
  {
    "name": "ericchu",
    "rank": 910
  },
  {
    "name": "youngle37",
    "rank": 911
  },
  {
    "name": "jameshsu",
    "rank": 912
  },
  {
    "name": "ivan0708",
    "rank": 913
  },
  {
    "name": "etien",
    "rank": 914
  },
  {
    "name": "gary50613",
    "rank": 915
  },
  {
    "name": "pxh",
    "rank": 916
  },
  {
    "name": "sa072686",
    "rank": 917
  },
  {
    "name": "kuojack",
    "rank": 918
  },
  {
    "name": "oliver",
    "rank": 919
  },
  {
    "name": "henrychy",
    "rank": 920
  },
  {
    "name": "mmm",
    "rank": 921
  },
  {
    "name": "haribo0915",
    "rank": 922
  },
  {
    "name": "fisheep",
    "rank": 923
  },
  {
    "name": "brianhsu",
    "rank": 924
  },
  {
    "name": "andy_0323",
    "rank": 925
  },
  {
    "name": "jao20000321",
    "rank": 926
  },
  {
    "name": "morrischen",
    "rank": 927
  },
  {
    "name": "mikulove",
    "rank": 928
  },
  {
    "name": "dirk514121",
    "rank": 929
  },
  {
    "name": "esther_t",
    "rank": 930
  },
  {
    "name": "benson0402",
    "rank": 931
  },
  {
    "name": "i-lun",
    "rank": 932
  },
  {
    "name": "pclh",
    "rank": 933
  },
  {
    "name": "ericchanggggg",
    "rank": 934
  },
  {
    "name": "leofufu",
    "rank": 935
  },
  {
    "name": "jaes1237712",
    "rank": 936
  },
  {
    "name": "tigerwolf0713",
    "rank": 937
  },
  {
    "name": "puppy",
    "rank": 938
  },
  {
    "name": "cheng",
    "rank": 939
  },
  {
    "name": "yang747yang",
    "rank": 940
  },
  {
    "name": "alanqq0624",
    "rank": 941
  },
  {
    "name": "ted_yu",
    "rank": 942
  },
  {
    "name": "qqorange",
    "rank": 943
  },
  {
    "name": "qwertyuiop",
    "rank": 944
  },
  {
    "name": "tang891228",
    "rank": 945
  },
  {
    "name": "chonan1101",
    "rank": 946
  },
  {
    "name": "jeffzed",
    "rank": 947
  },
  {
    "name": "c121563701",
    "rank": 948
  },
  {
    "name": "thdob",
    "rank": 949
  },
  {
    "name": "octopuschou",
    "rank": 950
  },
  {
    "name": "ivyhuang",
    "rank": 951
  },
  {
    "name": "icy_summer",
    "rank": 952
  },
  {
    "name": "thepainters",
    "rank": 953
  },
  {
    "name": "octopus",
    "rank": 954
  },
  {
    "name": "speck",
    "rank": 955
  },
  {
    "name": "hahahahaha12",
    "rank": 956
  },
  {
    "name": "lsb666",
    "rank": 957
  },
  {
    "name": "cies96035",
    "rank": 958
  },
  {
    "name": "h44451890",
    "rank": 959
  },
  {
    "name": "as01671",
    "rank": 960
  },
  {
    "name": "jemmy",
    "rank": 961
  },
  {
    "name": "dudhfysibw1027",
    "rank": 962
  },
  {
    "name": "uccu1478",
    "rank": 963
  },
  {
    "name": "andrew704",
    "rank": 964
  },
  {
    "name": "meowmeowman",
    "rank": 965
  },
  {
    "name": "kirby5411",
    "rank": 966
  },
  {
    "name": "sqzze17231",
    "rank": 967
  },
  {
    "name": "yvonne852",
    "rank": 968
  },
  {
    "name": "ryantu",
    "rank": 969
  },
  {
    "name": "liu0105",
    "rank": 970
  },
  {
    "name": "gc1234",
    "rank": 971
  },
  {
    "name": "ja930036",
    "rank": 972
  },
  {
    "name": "davidavid",
    "rank": 973
  },
  {
    "name": "t510599",
    "rank": 974
  },
  {
    "name": "andrew",
    "rank": 975
  },
  {
    "name": "baaldiablo2",
    "rank": 976
  },
  {
    "name": "hsuan",
    "rank": 977
  },
  {
    "name": "justinqaq",
    "rank": 978
  },
  {
    "name": "jaxon",
    "rank": 979
  },
  {
    "name": "markmarkchen",
    "rank": 980
  },
  {
    "name": "austin",
    "rank": 981
  },
  {
    "name": "kunzhe",
    "rank": 982
  },
  {
    "name": "chiayen",
    "rank": 983
  },
  {
    "name": "yayun901001",
    "rank": 984
  },
  {
    "name": "h126015689",
    "rank": 985
  },
  {
    "name": "ellen",
    "rank": 986
  },
  {
    "name": "jakao",
    "rank": 987
  },
  {
    "name": "ak292987ka",
    "rank": 988
  },
  {
    "name": "abcmackabc",
    "rank": 989
  },
  {
    "name": "xxx",
    "rank": 990
  },
  {
    "name": "grasonyang",
    "rank": 991
  },
  {
    "name": "hyk_129",
    "rank": 992
  },
  {
    "name": "yhtang1019",
    "rank": 993
  },
  {
    "name": "cgjason",
    "rank": 994
  },
  {
    "name": "time_to_ac",
    "rank": 995
  },
  {
    "name": "secminhrian",
    "rank": 996
  },
  {
    "name": "asdfgh",
    "rank": 997
  },
  {
    "name": "emilan",
    "rank": 998
  },
  {
    "name": "dove3004",
    "rank": 999
  },
  {
    "name": "willpeng0723",
    "rank": 1000
  }
]